Tool.py
wdtestlib/__init__.py
wdtestlib/szlibone.py
wdtestlib-1.0.0.dist-info/LICENSE.txt
wdtestlib-1.0.0.dist-info/METADATA
wdtestlib-1.0.0.dist-info/WHEEL
wdtestlib-1.0.0.dist-info/top_level.txt
wdtestlib-1.0.0.dist-info/RECORD
