Metadata-Version: 2.1
Name: wdtestlib
Version: 1.0.0
Summary: this is a awesome lib
Home-page: https://github.com/wangshunzi/Python_code
Author: Sz
Author-email: 501562071@qq.com
License: MIT
Platform: UNKNOWN
